{
    "BW_common.078.0000": "水夫",
    "BW_common.078.0001": "小柳",
    "BW_common.078.0002": "水吉",
    "BW_common.078.0003": "拉修",
    "BW_common.078.0004": "柳助",
    "BW_common.078.0005": "飞卫门",
    "BW_common.078.0006": "燃信",
    "BW_common.078.0007": "赤带",
    "BW_common.078.0008": "崩巴",
    "BW_common.078.0009": "冰间",
    "BW_common.078.0010": "米兹艾特",
    "BW_common.078.0011": "小豪",
    "BW_common.078.0012": "奇拉利拉",
    "BW_common.078.0013": "阿豆",
    "BW_common.078.0014": "泽布拉",
    "BW_common.078.0015": "小咪",
    "BW_common.078.0016": "郁香香",
    "BW_common.078.0017": "卢兹",
    "BW_common.078.0018": "阿圆",
    "BW_common.078.0019": "莫艾奇",
    "BW_common.078.0020": "布拉泽",
    "BW_common.078.0021": "梅尔造",
    "BW_common.078.0022": "布太郎",
    "BW_common.078.0023": "足轻",
    "BW_common.078.0024": "布拉博",
    "BW_common.078.0025": "药膳",
    "BW_common.078.0026": "艾比",
    "BW_common.078.0027": "纳谷罗",
    "BW_common.078.0028": "巴欧",
    "BW_common.078.0029": "巴德盖",
    "BW_common.078.0030": "水之助",
    "BW_common.078.0031": "布罗林",
    "BW_common.078.0032": "莉莉",
    "BW_common.078.0033": "小咪",
    "BW_common.078.0034": "高西卡",
    "BW_common.078.0035": "篝火",
    "BW_common.078.0036": "吉奥化壶",
    "BW_common.078.0037": "笨笨",
    "BW_common.078.0038": "加农",
    "BW_common.078.0039": "夸雷",
    "BW_common.078.0040": "毕格瓦鲁",
    "BW_common.078.0041": "布雷兹",
    "BW_common.078.0042": "伍德",
    "BW_common.078.0043": "米琪",
    "BW_common.078.0044": "呱里奥",
    "BW_common.078.0045": "利兹米",
    "BW_common.078.0046": "马萨",
    "BW_common.078.0047": "奇拉莉娜",
    "BW_common.078.0048": "法乌娜",
    "BW_common.078.0049": "蒂亚",
    "BW_common.078.0050": "大风"
}
