{
    "DP.568.0000": "名字",
    "DP.568.0001": "基地的旗",
    "DP.568.0002": "ＩＤ",
    "DP.568.0003": "：",
    "DP.568.0004": "[0101,0000]",
    "DP.568.0005": "[0136,0006]",
    "DP.568.0006": "ＳＣＯＲＥ",
    "DP.568.0007": "遇到的人数",
    "DP.568.0008": "给予货物的次数",
    "DP.568.0009": "取得旗的次数",
    "DP.568.0010": "挖到玉的次数",
    "DP.568.0011": "挖到化石的次数",
    "DP.568.0012": "挖到陷阱的次数",
    "DP.568.0013": "[0139,0006]",
    "DP.568.0014": " ",
    "DP.568.0015": " ",
    "DP.568.0016": " ",
    "DP.568.0017": " ",
    "DP.568.0018": " ",
    "DP.568.0019": " ",
    "DP.568.0020": "正常旗",
    "DP.568.0021": "青铜旗",
    "DP.568.0022": "白银旗",
    "DP.568.0023": "黄金旗",
    "DP.568.0024": "白金旗",
    "DP.568.0025": "白金旗",
    "DP.568.0026": "白金旗",
    "DP.568.0027": "白金旗",
    "DP.568.0028": "白金旗",
    "DP.568.0029": "白金旗",
    "DP.568.0030": "白金旗",
    "DP.568.0031": "白金旗",
    "DP.568.0032": "写着什么\n……\\f\n目前为止获得的\nＳＣＯＲＥ　[0139,0006]",
    "DP.568.0033": "写着什么\n……\\f\n目前为止在地下所遇到的\n人数\\r\n[0137,0006]人！",
    "DP.568.0034": "写着什么\n……\\f\n目前为止\n给予道具的次数\\r\n[0137,0006]次！",
    "DP.568.0035": "写着什么\n……\\f\n目前为止拿到秘密基地\n旗的次数。\\r\n[0137,0006]次！",
    "DP.568.0036": "写着什么\n……\\f\n目前为止在地下\n挖掘玉的次数。\\r\n[0137,0006]次！",
    "DP.568.0037": "写着什么\n……\\f\n目前为止在地上\n挖掘化石的次数。\\r\n[0137,0006]次！",
    "DP.568.0038": "写着什么\n……\\f\n目前为止在地上让其他人中\n陷阱的次数。\\r\n[0137,0006]次！",
    "DP.568.0039": "写着什么\n……\\f\n目前为止自己中\n陷阱的次数。\\r\n[0137,0006]次！",
    "DP.568.0040": "写着什么\n……\\f\n目前为止在地下救助别人\n的次数。\\r\n[0137,0006]次！",
    "DP.568.0041": "写着什么\n……\\f\n目前为止在地下\n获得道具的次数。\\r\n[0137,0006]次！",
    "DP.568.0042": "写着什么\n……\\f\n目前为止在自己的基地\n被拿走旗的次数。\\r\n[0137,0006]次　……",
    "DP.568.0043": "写着什么\n……\\f\n目前为止在地下被夺走\n旗后又夺回来的次数。\\r\n[0137,0006]次！",
    "DP.568.0044": "写着什么\n……\\f\n目前为止在地下\n搬家的次数。\\r\n[0137,0006]次！",
    "DP.568.0045": "写着什么\n……\\f\n目前为止在地下将获得的旗\n登录到电脑上的次数。\\r\n[0137,0006]次！"
}
