{
  "DP.365.0000": "Cheri",
  "DP.365.0001": "Chesto",
  "DP.365.0002": "Pecha",
  "DP.365.0003": "Rawst",
  "DP.365.0004": "Aspear",
  "DP.365.0005": "Leppa",
  "DP.365.0006": "Oran",
  "DP.365.0007": "Persim",
  "DP.365.0008": "Lum",
  "DP.365.0009": "Sitrus",
  "DP.365.0010": "Figy",
  "DP.365.0011": "Wiki",
  "DP.365.0012": "Mago",
  "DP.365.0013": "Aguav",
  "DP.365.0014": "Iapapa",
  "DP.365.0015": "Razz",
  "DP.365.0016": "Bluk",
  "DP.365.0017": "Nanab",
  "DP.365.0018": "Wepear",
  "DP.365.0019": "Pinap",
  "DP.365.0020": "Pomeg",
  "DP.365.0021": "Kelpsy",
  "DP.365.0022": "Qualot",
  "DP.365.0023": "Hondew",
  "DP.365.0024": "Grepa",
  "DP.365.0025": "Tamato",
  "DP.365.0026": "Cornn",
  "DP.365.0027": "Magost",
  "DP.365.0028": "Rabuta",
  "DP.365.0029": "Nomel",
  "DP.365.0030": "Spelon",
  "DP.365.0031": "Pamtre",
  "DP.365.0032": "Watmel",
  "DP.365.0033": "Durin",
  "DP.365.0034": "Belue",
  "DP.365.0035": "Occa",
  "DP.365.0036": "Passho",
  "DP.365.0037": "Wacan",
  "DP.365.0038": "Rindo",
  "DP.365.0039": "Yache",
  "DP.365.0040": "Chople",
  "DP.365.0041": "Kebia",
  "DP.365.0042": "Shuca",
  "DP.365.0043": "Coba",
  "DP.365.0044": "Payapa",
  "DP.365.0045": "Tanga",
  "DP.365.0046": "Charti",
  "DP.365.0047": "Kasib",
  "DP.365.0048": "Haban",
  "DP.365.0049": "Colbur",
  "DP.365.0050": "Babiri",
  "DP.365.0051": "Chilan",
  "DP.365.0052": "Liechi",
  "DP.365.0053": "Ganlon",
  "DP.365.0054": "Salac",
  "DP.365.0055": "Petaya",
  "DP.365.0056": "Apicot",
  "DP.365.0057": "Lansat",
  "DP.365.0058": "Starf",
  "DP.365.0059": "Enigma",
  "DP.365.0060": "Micle",
  "DP.365.0061": "Custap",
  "DP.365.0062": "Jaboca",
  "DP.365.0063": "Rowap"
}