{
    "B2W2_script.405.0000": "シャガ『きみが　のぞむなら\nきみの　ポケモンに\\r\nドラゴンタイプ　さいきょうの\\r\nわざを　おしえても　よい\\f\nさて　ポケモンに\nわざを　おぼえさせるかね？\\f",
    "B2W2_script.405.0001": "よろしい\nきが　むいたなら　また　きたまえ",
    "B2W2_script.405.0002": "フム……\\f\nきみが　つれている　ポケモンは\nわざを　おぼえることは　できる\\f\nだが　その　ポケモンは　まだ\nきみに　かんぜんに　なついていない\\f\nそれでは　この　わざを\nおぼえさせる　わけには　いかない",
    "B2W2_script.405.0003": "なるほど……\\f\nだが　きみが　つれている　なかに\nわざを　おぼえられる\\r\nポケモンは　いないようだね",
    "B2W2_script.405.0004": "どの　ポケモンに\nわざを　おぼえさせるのかね？\\f",
    "B2W2_script.405.0005": "もうしわけないのだが……\\f\nその　ポケモンでは\nこの　わざは　おぼえられない",
    "B2W2_script.405.0006": "フム……\\f\nタマゴに　わざを　おぼえさせるのは\nわたしにも　むずかしいな",
    "B2W2_script.405.0007": "ふむ……　その　ポケモンは\nすでに　[0107,0000]を　おぼえているが",
    "B2W2_script.405.0008": "シャガ『りゅうせいぐんの　いりょくは\nすさまじいが　つかうと　じぶんの\\r\nとくこうも　さげてしまうぞ",
    "B2W2_script.405.0009": "[0101,0000]に　わざを\nおぼえさせるのを　あきらめますか？",
    "B2W2_script.405.0010": "[0101,0000]は　あたらしく\n[0107,0001]を　おぼえた！",
    "B2W2_script.405.0011": "[0101,0000]は　あたらしく\n[0107,0001]を　おぼえたい……！\\f\nしかし　[0101,0000]は\nすでに　わざを　４つ　おぼえている！\\f\n[0107,0001]の　かわりに\nほかの　わざを　わすれさせますか？",
    "B2W2_script.405.0012": "それでは　[0107,0000]を\nおぼえさせるのを　あきらめますか？",
    "B2W2_script.405.0013": "[0101,0000]は　[0107,0001]を\nおぼえずに　おわった！",
    "B2W2_script.405.0014": "[0107,0001]を\nわすれさせて　よろしいですね？",
    "B2W2_script.405.0015": "１　２の　……ポカン！\\f\n[0101,0000]は　[0107,0001]の\nつかいかたを　きれいに　わすれた！\\f\nそして……！\\f\n[0101,0000]は　あたらしく\n[0107,0002]を　おぼえた！",
    "B2W2_script.405.0016": "アイリス『ねえねえ！\nよければ　きみの　ポケモンに\\r\nドラゴンタイプ　さいきょうの　わざ\\r\nあたしが　おしえてあげる！！\\f\nどうする？　ポケモンに\nわざを　おぼえさせてあげる？\\f",
    "B2W2_script.405.0017": "はーい！　それじゃあ\nきがむいたら　またきてね！！",
    "B2W2_script.405.0018": "どれどれ……\\f\nきみが　つれている　ポケモンは\nわざを　おぼえることは　できるけど\\f\nその　ポケモン……　まだ\nきみに　かんぜんに　なついてないよね\\f\nそれだと　この　わざを\nおぼえさせるのは　むずかしいなあ",
    "B2W2_script.405.0019": "えーっと\\f\nきみが　つれている　なかに\nわざを　おぼえられる\\r\nポケモン　いないみたい……",
    "B2W2_script.405.0020": "どの　ポケモンに\nわざを　おぼえさせるの？\\f",
    "B2W2_script.405.0021": "うーん　ごめんね……\\f\nその　ポケモンでは\nこの　わざ　おぼえられないよ……",
    "B2W2_script.405.0022": "エーッ！\\f\nタマゴに　わざを　おぼえさせるの？\nじゃあ　ちょっと　がんばってみるね\\f\n……　……　……\n……　……　……\\f\nごめん……\nちょっと　ムリみたい……",
    "B2W2_script.405.0023": "どれどれ？　その　ポケモン\nすでに　[0107,0000]を　おぼえているよ？",
    "B2W2_script.405.0024": "アイリス『りゅうせいぐんの　いりょくは\nものすごーく　すごいんだけど！\\f\nつかったあとは　じぶんの\nとくこうも　さがっちゃうんだ"
}
