{
    "HGSS.568.0000": "I... I’m in shock!\\f\nA guy about your age with piercing\neyes and long hair came in.\\f\nHe scared me into giving him my\nprized Pokémon!\\f\nI still have one left, but what if\nhe comes back?\\f\nYou look strong.\nCould you look after my Pokémon\\r\nfor a while? [0200,0000]",
    "HGSS.568.0001": "Oh, thank you!\nTake good care of it, please!\\f",
    "HGSS.568.0002": "[0103,0000,0000] received\na Pokémon!",
    "HGSS.568.0003": "Your Pokémon party is full.",
    "HGSS.568.0004": "Oh, no... What’ll I do if he comes back?",
    "HGSS.568.0005": "Hi! How’s my Pokémon?\\f\nI think I’m safe now, so may I have\nit back? [0200,0000]",
    "HGSS.568.0006": "Hi! How’s my Pokémon?",
    "HGSS.568.0007": "Thank you!",
    "HGSS.568.0008": "Hey, that’s not my Pokémon.",
    "HGSS.568.0009": "My Pokémon has come to like you.\\f\nAll right, you should keep it.\nBut promise to be good to it!",
    "HGSS.568.0010": "Oh, no, no...\nThat’s the same as being robbed.",
    "HGSS.568.0011": "For Pokémon, happiness is being\nwith a person who treats them well.",
    "HGSS.568.0012": "Huh?\nIt’s holding an item.\\r\nYou should keep that.",
    "HGSS.568.0013": "Huh?\nIts Poké Ball has a Ball Capsule on it!\\r\nPlease remove it.",
    "HGSS.568.0014": "Huh?\nYou...only have one Pokémon!\\r\nYou can’t give it back to me then."
}
