{
    "B2W2_common.185.0000": "スーツアクター",
    "B2W2_common.185.0001": "バトルシップ",
    "B2W2_common.185.0002": "ハチクマン『ファファ！！\\f\nハチクほうの　いりょく！！\nみを　もって　しるが　よいっ！",
    "B2W2_common.185.0003": "ハチクマン『ファファファ……\\f\nわがはいの　ずのうと\nハチクほうの　ちからが\\r\nあれば　このせかい　など……",
    "B2W2_common.185.0004": "ハチクマン『まだまだ……\nわがはいは　こんなことでは\\r\nたおれぬぞ……",
    "B2W2_common.185.0005": "ハチクマン『グムム……\nこんなことに　なろうとは……",
    "B2W2_common.185.0006": "ハチクマン『グッ……　からだが……",
    "B2W2_common.185.0007": "ハチクマン『グッ……\nおもうように　うごけぬ……",
    "B2W2_common.185.0008": "ハチクマン『これまで……　か……",
    "B2W2_common.185.0009": "ハチクマン『ゼエッ……　ゼエッ……",
    "B2W2_common.185.0010": "[0102,0000]ガール『なんなの……\nこの　きょだいな　マシンは……\\f\nしかも　マシンに　そうびされた\nきかいの　なか　から\\r\nハチクマンさんが　とびだしてきた……",
    "B2W2_common.185.0011": "ハチクマン『ファファファ！！\nみたか！　これが　わがはいの\\r\nかいはつした　バトルシップ！\\f\nそのなも　ハチクかん！！\\f\nそして　ハチクかんの　そうびは\nあの　ごうかきゃくせん　から\\r\nぬすみだした　ブラックダイヤの\\r\nパワーを　りようした　マシン！\\r\nそのなも　ハチクほうだっ！　",
    "B2W2_common.185.0012": "[0102,0000]ガール『……\nハチクほう　ですって……？\\f\n……っていうか　けっきょく　あのまま\nおよいで　ごうかきゃくせんに\\r\nしのびこんで　ブラックダイヤを\\r\nぬすみだした　ってこと……\\f\nバカみたい……",
    "B2W2_common.185.0013": "ハチクマン『この　ハチクほうは\nきょうりょくな　エネルギーとともに\\r\nあらゆるものを　はっしゃする\\r\nちょうこうせいのう　マシン！\\f\nしかも　ブラックダイヤこうかに　より\nはっしゃ　した　もの　の\\r\nのうりょくを　なんばいにも\\r\nパワーアップ　するのだっ！",
    "B2W2_common.185.0014": "[0102,0000]ガール『もう……\nなんて　ふざけた　ものを……",
    "B2W2_common.185.0015": "ハチクマン『ファファファ！！\\f\nさあ！　かくごは　よいか！？\n[0102,0000]ガール！！",
    "B2W2_common.185.0016": "[0102,0000]ガール『らくしょうよ！",
    "B2W2_common.185.0017": "ハチクマン『ファファファ！\\f\nおろかなり！　[0102,0000]ガール！\nわがはいの　しんの　じつりょく！\\r\nおもいしるが　よいわっ！！",
    "B2W2_common.185.0018": "[0102,0000]ガール『もう　ダメかも……",
    "B2W2_common.185.0019": "ハチクマン『ファファファ！\\f\nそうだ！　[0102,0000]ガール！！\nぜつぼうに　もだえるが　いいっ！！",
    "B2W2_common.185.0020": "[0102,0000]ガール『……いくよっ！！",
    "B2W2_common.185.0021": "ハチクマン『ファー　ファファファ！！\nそれでこそ　わがはいの　エモノよ！！",
    "B2W2_common.185.0022": "[0102,0000]ガール『にげようかな……",
    "B2W2_common.185.0023": "ハチクマン『ファファファ！！\nいまさら　にがしは　せぬぞ！\\f\nきょうが　[0102,0000]ガールの\nめいにちと　なるのだっ！",
    "B2W2_common.185.0024": "ハチクマン『ファファファ！！\nすばらしいぞ！　ハチクかん！！\\r\nそして　ハチクほうの　いりょく！！",
    "B2W2_common.185.0025": "[0102,0000]ガール『つよい……\\f\nこれが　ブラックダイヤを\nりようした　パワーなの……",
    "B2W2_common.185.0026": "ハチクマン『ファファファ！！\nこのひを　まちのぞんでいたぞ！\\f\nきさまを　たおすために　いままで\nついやした　じかんも……\\f\n……グッ！？",
    "B2W2_common.185.0027": "[0102,0000]ガール『……？",
    "B2W2_common.185.0028": "ハチクマン『グハッ！！\nゴフッ！　ゴフッ！！　ゴフーッ！！",
    "B2W2_common.185.0029": "[0102,0000]ガール『なに……？",
    "B2W2_common.185.0030": "ハチクマン『グムム……　もしや……",
    "B2W2_common.185.0031": "[0102,0000]ガール『どうしたの！？",
    "B2W2_common.185.0032": "ハチクマン『クッ！　なんでもないわ！\nさっさと　かかって　こんかっ！",
    "B2W2_common.185.0033": "[0102,0000]ガール『チャンスね……",
    "B2W2_common.185.0034": "ハチクマン『ええい！　あまいわっ！\nわがはいに　スキなど　ありはせぬ！",
    "B2W2_common.185.0035": "[0102,0000]ガール『いくわよっ！！",
    "B2W2_common.185.0036": "ハチクマン『ファ……　ファファ！！\\f\nきさまを　たおし　このよを\nわがものに　してくれるっ！！",
    "B2W2_common.185.0037": "[0102,0000]ガール『……",
    "B2W2_common.185.0038": "ハチクマン『クッ！　どうした！？\\f\nそちらが　こぬならば\nこちらから　いくぞっ！！",
    "B2W2_common.185.0039": "ハチクマン『ファファファ！！\nどうだ！　[0102,0000]ガール！\\f\nわがはいの　おそろしさを\nおもいしったか！！",
    "B2W2_common.185.0040": "[0102,0000]ガール『うう……\nわたしも　[0102,0000]も\\r\nもう　うごくことも　できない……",
    "B2W2_common.185.0041": "ハチクマン『ファファファ！！\n[0102,0000]ガールよ！！\\f\nいままで　せわに　なった\nれいを　してやろう……",
    "B2W2_common.185.0042": "[0102,0000]ガール『え……？",
    "B2W2_common.185.0043": "ハチクマン『ファファファ！！\nこの　ハチクほうで　きさまを\\r\nふきとばして　やろうっ！！",
    "B2W2_common.185.0044": "[0102,0000]ガール『えっ……\nそんな　まって……　やめて……",
    "B2W2_common.185.0045": "ハチクマン『ファファファ！！\nよぞらに　きらめく　ほしと　なれい！\\f\nハチクほう！　はっしゃーーーッ！！",
    "B2W2_common.185.0046": "[0102,0000]ガール『フギャーッ！！",
    "B2W2_common.185.0047": "ハチクマン『ファファファ！！\nさらばだ！！　[0102,0000]ガール！",
    "B2W2_common.185.0048": "……ハチクマンの　ひみつへいき\nハチクほうに　よって\\r\nそらの　かなたへと　ちった\\r\n[0102,0000]ガール！！\\f\nかのじょの　きえた　ほうがくには\nおおきな　ほしが　ひとつ\\r\nひかっていると　いう……\\f\nさらば！\n[0102,0000]ガール！！\\f\nありがとう！\n[0102,0000]ガール！！\\f",
    "B2W2_common.185.0049": "ハチクマン『グフォ！！",
    "B2W2_common.185.0050": "[0102,0000]ガール『ハチクマンさん！！",
    "B2W2_common.185.0051": "ハチクマン『ヌオオ……",
    "B2W2_common.185.0052": "[0102,0000]ガール『もう　やめよ……\nハチクマンさん……",
    "B2W2_common.185.0053": "ハチクマン『……わが　やぼうも\nここまでか　ファファファ……\\f\n[0102,0000]ガール　よ……\nさあ　とどめを　さすが　いい……",
    "B2W2_common.185.0054": "[0102,0000]ガール『……ダメ\nそんなこと　わたし　できない……　",
    "B2W2_common.185.0055": "ハチクマン『なんだと……\\f\nきさま……　このわがはいに\nなさけでも　かける　つもりかっ！？",
    "B2W2_common.185.0056": "[0102,0000]ガール『ちがうの……\\f\nいままでの　たたかいで\nきが　ついたんだ……\\f\nたしかに　あなたは　おそろしい\nあくの　かいじん……\\f\nでも　それ　いぜんに　ひとりの\nイカした　トレーナー　だって……",
    "B2W2_common.185.0057": "ハチクマン『[0102,0000]ガール……",
    "B2W2_common.185.0058": "[0102,0000]ガール『そんな　あなたが\nいなくなっちゃうのは　イヤなの……\\f\nだから……",
    "B2W2_common.185.0059": "ハチクマン『……　……",
    "B2W2_common.185.0060": "[0102,0000]ガール『だから……\nいまは　かえって……\\f\nそして……\\f\nそして　からだを　ととのえたら\nまた　わたしと　たたかいましょ……",
    "B2W2_common.185.0061": "ハチクマン『……　……\\f\n[0102,0000]ガール……\nきょうのひの　ことは　わすれぬ……\\f\nそして　きさまの　ことも　な……\\f\nいつのひか　かならず\nけっちゃくを　つけてやる……",
    "B2W2_common.185.0062": "[0102,0000]ガール『ハチクマンさん……",
    "B2W2_common.185.0063": "ハチクマン『それまで　くびを\nあらって　まっていろっ！！\\r\nよいな！　[0102,0000]ガール！！\\f\nいや！　すばらしき\nわが　ライバル　よ！！",
    "B2W2_common.185.0064": "ハチクマンと　[0102,0000]ガール……\\f\nくりかえされる　たたかいの　なかで\nいつしか　ふたりは　おたがいを\\r\nみとめあって　いた……\\f\nさいせんを　ちかう　ふたりを\nつきあかりが　やさしく　てらす……\\f\nありがとう！\nハチクマン！！\\f\nありがとう！\n[0102,0000]ガール！！",
    "B2W2_common.185.0065": "ハチクマン『……グッ！　グフッ！！",
    "B2W2_common.185.0066": "[0102,0000]ガール『ハチクマンさん！！",
    "B2W2_common.185.0067": "ハチクマン『ヌオオ……\\f\nやはりか……\\f\nハチクほうの　エネルギーは\nかいじんの　からだには\\r\nふたんが　あったか……",
    "B2W2_common.185.0068": "[0102,0000]ガール『……おわりよ\nかんねんして　ハチクマンさん……",
    "B2W2_common.185.0069": "ハチクマン『グッ！　グフォ！！\nヌウウ……　もはや　これまでか……",
    "B2W2_common.185.0070": "[0102,0000]ガール『ほら……\nわたしのてに　つかまって……",
    "B2W2_common.185.0071": "ハチクマン『うるさいわ……\\f\nかいじんが……　グッ……\nヒロインの　てなど　かりるか……\\f\nグッ！　グフッ！　グフォッ！！",
    "B2W2_common.185.0072": "[0102,0000]ガール『そんな……",
    "B2W2_common.185.0073": "ハチクマン『グフッ！！　グフッ！！\\f\nかいじんには……　かいじんの\nいきざまと　いうものが　ある……\\f\nみているが　いい……",
    "B2W2_common.185.0074": "[0102,0000]ガール『ちょっと……",
    "B2W2_common.185.0075": "ハチクマン『ハチクかん　よ！！\\f\nハチクほうを　わがはいに\nむけて　はっしゃ　するのだ！！",
    "B2W2_common.185.0076": "[0102,0000]ガール『やめてっ！！\nハチクほうを　とめてーーっ！！",
    "B2W2_common.185.0077": "ハチクマン『ファファファ！！\\f\n……　……わがはいは\nげんじつと　げんそうを　さまよう\\r\nあくのかいじん　ハチクマン……\\f\nさらばだ！　[0102,0000]ガール！！\nファ！！　ファファファファファー！！",
    "B2W2_common.185.0078": "[0102,0000]ガール『ハチクマンさん！！",
    "B2W2_common.185.0079": "みずからの　はいぼくを　うけいれた\nハチクマンは　ハチクほうに\\r\nよって　よぞらに　ちった……\\f\nあくのかいじんは　さった……\\f\nしかし　[0102,0000]ガールの　むねには\nいつまでも　かれの　わらいごえが\\r\nこだま　するの　だった……\\f\nさらば！　かいじんハチクマン！",
    "B2W2_common.185.0080": "ハチクマン『ファファファ……\\f\nせいぎの　ヒロインで　ありながら\nそのような　わざを　つかうとは……",
    "B2W2_common.185.0081": "[0102,0000]ガール『なにがわるいの！\\f\nわたしは　せいぎの　ためなら\nしゅだんは　えらんだりしないわ！",
    "B2W2_common.185.0082": "ハチクマン『ファファファ……\nわがはいのような　セリフを　はく……\\f\nせいぎの　ヒロインに　しておくには\nいささか　おしい　じんざいよ……\\f\nどうだ？　ヒロインなど　やめて\nわがはいの　ぶかに　ならぬか？",
    "B2W2_common.185.0083": "[0102,0000]ガール『ありえないわ！\\f\nあなたこそ　あくのかいじんを　やめ\nわたしと　いっしょに　せいぎのみちを\\r\nあゆめば　いいじゃない！",
    "B2W2_common.185.0084": "ハチクマン『ファーファファ！！\nありえぬ！！　ありえぬなっ！！\\f\nともを　うらぎり　かぞくを　すてて\nあゆんできた　かいじんの　みち……\\f\nわがじんせい　しょうがい　かいじん！\nあくのみちを　しょうじんする　のみ！"
}
