{
    "B2W2_script.653.0000": "女孩子：啊！阿戴克先生，\n要鍛鍊這個人嗎？\\f",
    "B2W2_script.653.0001": "男孩子：哎？但是\n這個人看起來很強啊！\\f",
    "B2W2_script.653.0002": "阿戴克：哦！是很強，\n但是失敗也是很好的老師。\\f\n最重要的是享受神奇寶貝對戰！\\f",
    "B2W2_script.653.0003": "就是這樣，[0100,0000]！\n你和他們過過招吧！\\f",
    "B2W2_script.653.0004": "那就讓你看看我的\n神奇寶貝的可愛之處吧！\\f",
    "B2W2_script.653.0005": "剛才的較量\n非常精彩！\\f\n那麼，接下來……\\f",
    "B2W2_script.653.0006": "是！\\f",
    "B2W2_script.653.0007": "阿戴克：在那之前，先回復一下\n[0100,0000]的神奇寶貝。\\f",
    "B2W2_script.653.0008": "女孩子：對戰勝負是靠\n屬性相剋來決定的！\\f",
    "B2W2_script.653.0009": "阿戴克：真是驚心動魄的\n戰鬥啊！\\f\n我感受到了每一隻神奇寶貝\n喜悅的心情！\\f",
    "B2W2_script.653.0010": "怎麼樣，[0100,0000]！\\f\n神奇寶貝的屬性對\n戰鬥很重要吧。\\f\n水屬性克炎屬性，\n炎屬性克草屬性，\\r\n草屬性克水屬性……\\f\n當然屬性並不能\n代表一切！\\f",
    "B2W2_script.653.0011": "但是但是！\\f\n神奇寶貝的屬性如果\n和技能的屬性一樣，\\r\n技能威力就會提升！\\f",
    "B2W2_script.653.0012": "那麼，給如此\n努力的神奇寶貝回復體力吧！\\f\n[0101,0001]！\n為了[0100,0000]，你做得很好！\\f",
    "B2W2_script.653.0013": "神奇寶貝和人的\n相遇……\\r\n這就是旅程的美妙！",
    "B2W2_script.653.0014": "阿戴克：哦！\n你得到道館徽章了啊。\\f\n這是你理解了\n和你一同戰鬥的神奇寶貝，\\r\n引導出它們的能力的結果！",
    "B2W2_script.653.0015": "阿戴克：你有了這麼多徽章，\n真是了不起。\\f\n但是行百里者\n半九十……\\f\n強大究竟是什麼呢？",
    "B2W2_script.653.0016": "阿戴克：哦！你來了啊！\\f\n你已經是合眾地區\n最強的神奇寶貝訓練師了，\\r\n能讓我也領教一下嗎！",
    "B2W2_script.653.0017": "阿戴克：哦！你來了啊！\\f\n我想讓他們也瞭解一下\n訓練師的厲害。\\f\n好了，合眾地區\n最強的神奇寶貝訓練師，\\r\n能讓我也領教一下嗎！",
    "B2W2_script.653.0018": "哦哦！\n很激動啊！\\f\n那麼，訓練師阿戴克，\n參上！\\f",
    "B2W2_script.653.0019": "唔……\n那我就在這裡等你了。",
    "B2W2_script.653.0020": "阿戴克：真是厲害！\\f",
    "B2W2_script.653.0021": "？？？：爺爺！\\f\n成功了！\\f\n成功了！\\f\n成功了！！\\f\n黑色摩天樓！\\f\n我登到天際了！\\f",
    "B2W2_script.653.0022": "？？？：爺爺！\\f\n成功了！\\f\n成功了！\\f\n成功了！！\\f\n白色樹洞！\\f\n我走到最深處了！\\f",
    "B2W2_script.653.0023": "阿戴克：哦哦！\n這不是番石郎嗎！\\f\n剛才你說的\n是真的嗎？\\f",
    "B2W2_script.653.0024": "番石郎：喂！\\f\n爺爺。\\f\n我有多強\\f\n爺爺也是知道的吧！\\f\n話說。\\f",
    "B2W2_script.653.0025": "這傢伙是誰？\\f",
    "B2W2_script.653.0026": "阿戴克：他叫\n[0100,0000]！\\f\n是合眾最強的\n神奇寶貝訓練師。\\f",
    "B2W2_script.653.0027": "阿戴克：她叫\n[0100,0000]！\\f\n是合眾最強的\n神奇寶貝訓練師。\\f",
    "B2W2_script.653.0028": "番石郎：果然！\\f\n看起來就很強的樣子。\\f",
    "B2W2_script.653.0029": "阿戴克：怎麼樣，番石郎，\n要不要和他交交手？\\f",
    "B2W2_script.653.0030": "番石郎：不行！\\f\n我知道這傢伙很強。\\f\n我也想戰鬥！\\f\n但是這傢伙的神奇寶貝\\f\n還沒有吃夠苦！\\f",
    "B2W2_script.653.0031": "我！\\f\n和我自己的神奇寶貝！\\f\n登上了黑色摩天樓！\\f\n所以你也要這麼做！\\f\n到時候我們再比比看\\f\n誰更強！\\f",
    "B2W2_script.653.0032": "我！\\f\n和我自己的神奇寶貝！\\f\n徵服了白色樹洞！\\f\n所以你也要這麼做！\\f\n到時候我們再比比看\\f\n誰更強！\\f",
    "B2W2_script.653.0033": "再見了！\\f\n爺爺，[0100,0000]！\\f",
    "B2W2_script.653.0034": "阿戴克：我孫子\n還是那麼吵鬧啊！\\f\n他說的話就讓我來\n說明一下吧。\\f\n他挑戰的是在\n黑都市出現的一個叫\\r\n黑色摩天樓的地方。\\f\n你去了就知道那是什麼地方了。\\f\n不過一般的訓練師是\n到不了那傢伙所在的地方的。\\f\n所以！可以的話\n你也去挑戰吧。",
    "B2W2_script.653.0035": "阿戴克：我孫子\n還是那麼吵鬧啊！\\f\n他說的話就讓我來\n說明一下吧。\\f\n他挑戰的是在\n白森林出現的一個叫\\r\n白色樹洞的地方。\\f\n你去了就知道那是什麼地方了。\\f\n不過一般的訓練師是\n到不了那傢伙所在的地方的。\\f\n所以！可以的話\n你也去挑戰吧。",
    "B2W2_script.653.0036": "阿戴克：你要是找到了\n要做的事\\r\n就要毫不猶豫地去挑戰！\\f\n不要怕！\n有神奇寶貝在你身邊。\\f\n就算你一個人不行，\n有神奇寶貝在，就什麼事\\r\n都能辦到！",
    "B2W2_script.653.0037": "我的夢想就是\n在這裡培養神奇寶貝。\\f\n成為合眾地區\n最強的神奇寶貝訓練師！",
    "B2W2_script.653.0038": "想更瞭解神奇寶貝的話\n就要變得更強！\\f\n為此我也要去\n很多很多地方。",
    "B2W2_script.653.0039": "喲！\\f\n喲！\\f\n喲！！\\f\n說好了。\\f\n我和你！\\f\n一場最棒的對戰。\\f\n這是紀念！\\f\n好好培養這圓陸鯊吧！\\f",
    "B2W2_script.653.0040": "喲！\\f\n喲！\\f\n喲！！\\f\n說好了。\\f\n我和你！\\f\n一場最棒的對戰。\\f\n這是紀念！\\f\n好好培養這迷你龍吧！\\f",
    "B2W2_script.653.0041": "[0100,0000]得到了\n[0101,0001]！",
    "B2W2_script.653.0042": "要給[0101,0001]\n起名字嗎？",
    "B2W2_script.653.0043": "什麼啊！\\f\n你帶著的神奇寶貝滿了啊！\\f\n明白了。\\f\n明白了。\\f\n明白了！\\f\n我在這裡等你！",
    "B2W2_script.653.0044": "我認可你了！\\f\n一定要好好培養啊！\\f\n[0100,0000]！\\f\n我在黑色摩天樓等你！\\f",
    "B2W2_script.653.0045": "我認可你了！\\f\n一定要好好培養啊！\\f\n[0100,0000]！\\f\n我在白色樹洞等你！\\f"
}
