{
    "BW_common.112.0000": "とうく",
    "BW_common.112.0001": "とうそ",
    "BW_common.112.0002": "とうそうしん",
    "BW_common.112.0003": "とうも",
    "BW_common.112.0004": "とおせんほう",
    "BW_common.112.0005": "とーたくん",
    "BW_common.112.0006": "とーとー",
    "BW_common.112.0007": "とーとりお",
    "BW_common.112.0008": "とーふる",
    "BW_common.112.0009": "とおほえ",
    "BW_common.112.0010": "とーみらー",
    "BW_common.112.0011": "とかーす",
    "BW_common.112.0012": "ときとき",
    "BW_common.112.0013": "ときのほうこう",
    "BW_common.112.0014": "とく",
    "BW_common.112.0015": "とくい",
    "BW_common.112.0016": "とくかす",
    "BW_common.112.0017": "とくくらけ",
    "BW_common.112.0018": "とくけいる",
    "BW_common.112.0019": "とくしゆ",
    "BW_common.112.0020": "とくつき",
    "BW_common.112.0021": "とくとく",
    "BW_common.112.0022": "とくとくのきは",
    "BW_common.112.0023": "とくのこな",
    "BW_common.112.0024": "とくのとけ",
    "BW_common.112.0025": "とくはり",
    "BW_common.112.0026": "とくひし",
    "BW_common.112.0027": "とくほうそう",
    "BW_common.112.0028": "とくろつく",
    "BW_common.112.0029": "とくろをまく",
    "BW_common.112.0030": "とけきつす",
    "BW_common.112.0031": "とけきやのん",
    "BW_common.112.0032": "とけちつく",
    "BW_common.112.0033": "とけひー",
    "BW_common.112.0034": "とける",
    "BW_common.112.0035": "とこーむ",
    "BW_common.112.0036": "とさいとん",
    "BW_common.112.0037": "とさきんと",
    "BW_common.112.0038": "としよつち",
    "BW_common.112.0039": "とたいとす",
    "BW_common.112.0040": "とつこらー",
    "BW_common.112.0041": "とつしん",
    "BW_common.112.0042": "とつておき",
    "BW_common.112.0043": "とてつこつ",
    "BW_common.112.0044": "ととくらー",
    "BW_common.112.0045": "ととせるか",
    "BW_common.112.0046": "とひけり",
    "BW_common.112.0047": "とひはねる",
    "BW_common.112.0048": "とひひさけり",
    "BW_common.112.0049": "ともえなけ",
    "BW_common.112.0050": "ともたち",
    "BW_common.112.0051": "ともたちこーと",
    "BW_common.112.0052": "とらいあたつく",
    "BW_common.112.0053": "とらいある",
    "BW_common.112.0054": "とらこん",
    "BW_common.112.0055": "とらこんくろー",
    "BW_common.112.0056": "とらこんたいふ",
    "BW_common.112.0057": "とらこんてーる",
    "BW_common.112.0058": "とらひおん",
    "BW_common.112.0059": "とらんせる",
    "BW_common.112.0060": "とりつく",
    "BW_common.112.0061": "とりつくるーむ",
    "BW_common.112.0062": "とりてふす",
    "BW_common.112.0063": "とりととん",
    "BW_common.112.0064": "とりふるきつく",
    "BW_common.112.0065": "とりふるはとる",
    "BW_common.112.0066": "とりゆうす",
    "BW_common.112.0067": "とりるくちはし",
    "BW_common.112.0068": "とりるらいなー",
    "BW_common.112.0069": "とるねろす",
    "BW_common.112.0070": "とれいんはんち",
    "BW_common.112.0071": "とれーす",
    "BW_common.112.0072": "とれーなー",
    "BW_common.112.0073": "とれていあ",
    "BW_common.112.0074": "とろあそひ",
    "BW_common.112.0075": "とろかけ",
    "BW_common.112.0076": "とろはくたん",
    "BW_common.112.0077": "とろひうす",
    "BW_common.112.0078": "とろほう",
    "BW_common.112.0079": "とわすれ",
    "BW_common.112.0080": "とんからす",
    "BW_common.112.0081": "とんかん",
    "BW_common.112.0082": "とんふあん",
    "BW_common.112.0083": "とんほかえり",
    "BW_common.112.0084": "とんめる"
}
