{
    "BW_common.157.0000": "交換にだす",
    "BW_common.157.0001": "もどる",
    "BW_common.157.0002": "相手にみせる",
    "BW_common.157.0003": "つよさをみる",
    "BW_common.157.0004": "交換する",
    "BW_common.157.0005": "やめる",
    "BW_common.157.0006": "通信待機中！\nしばらく　お待ちください",
    "BW_common.157.0007": "パートナーとなる　相手に\n赤外線を　向けてください",
    "BW_common.157.0008": "リーダーになりました！",
    "BW_common.157.0009": "対戦相手の　リーダーに\n赤外線を　向けてください",
    "BW_common.157.0010": "しばらく　お待ちください",
    "BW_common.157.0011": "ともだちコード",
    "BW_common.157.0012": "フィーリングチェック",
    "BW_common.157.0013": "中断しますか？",
    "BW_common.157.0014": "交換する　相手に\n赤外線を　向けてください",
    "BW_common.157.0015": "ポケモン交換",
    "BW_common.157.0016": "手持ち",
    "BW_common.157.0017": "[0102,0000]と　[0102,0001]を\n交換しますか？",
    "BW_common.157.0018": "Ｌｖ．[0202,0000]",
    "BW_common.157.0019": "終了しますか？",
    "BW_common.157.0020": "交換しました",
    "BW_common.157.0021": "しばらく　お待ちください",
    "BW_common.157.0022": "遊ぶ内容が　違ったので\n最初に　もどります",
    "BW_common.157.0023": "ここまでの　活躍を\nポケモンレポートに　書き込みますか？",
    "BW_common.157.0024": "はい",
    "BW_common.157.0025": "いいえ",
    "BW_common.157.0026": "ポケモンレポートに　書き込んでいます\n電源を　切らないでください",
    "BW_common.157.0027": "No.[0202,0001]",
    "BW_common.157.0028": "[0101,0000]",
    "BW_common.157.0029": "[0102,0000]",
    "BW_common.157.0030": "ＨＰ",
    "BW_common.157.0031": "こうげき",
    "BW_common.157.0032": "ぼうぎょ",
    "BW_common.157.0033": "とくこう",
    "BW_common.157.0034": "とくぼう",
    "BW_common.157.0035": "すばやさ",
    "BW_common.157.0036": "せいかく",
    "BW_common.157.0037": "とくせい",
    "BW_common.157.0038": "もちもの",
    "BW_common.157.0039": "[0202,0000]／[0202,0001]",
    "BW_common.157.0040": "[0202,0000]",
    "BW_common.157.0041": "[0108,0000]",
    "BW_common.157.0042": "[0106,0000]",
    "BW_common.157.0043": "[0109,0000]",
    "BW_common.157.0044": "もっているわざ",
    "BW_common.157.0045": "[0107,0000]",
    "BW_common.157.0046": "♂",
    "BW_common.157.0047": "♀",
    "BW_common.157.0048": "[0100,0000]から\n[0102,0001]が　送られてきた",
    "BW_common.157.0049": "[0102,0001]を\n可愛がって　あげてね！",
    "BW_common.157.0050": "通信しています\nしばらく　お待ちください",
    "BW_common.157.0051": "みつけたい　ポケモンの\n頭文字を　選んでください",
    "BW_common.157.0052": "選んだ　頭文字のつく\nポケモンは　いません",
    "BW_common.157.0053": "[BD02]ア",
    "BW_common.157.0054": "[BD02]イ",
    "BW_common.157.0055": "[BD02]ウ",
    "BW_common.157.0056": "[BD02]エ",
    "BW_common.157.0057": "[BD02]オ",
    "BW_common.157.0058": "[BD02]カ",
    "BW_common.157.0059": "[BD02]キ",
    "BW_common.157.0060": "[BD02]ク",
    "BW_common.157.0061": "[BD02]ケ",
    "BW_common.157.0062": "[BD02]コ",
    "BW_common.157.0063": "[BD02]サ",
    "BW_common.157.0064": "[BD02]シ",
    "BW_common.157.0065": "[BD02]ス",
    "BW_common.157.0066": "[BD02]セ",
    "BW_common.157.0067": "[BD02]ソ",
    "BW_common.157.0068": "[BD02]タ",
    "BW_common.157.0069": "[BD02]チ",
    "BW_common.157.0070": "[BD02]ツ",
    "BW_common.157.0071": "[BD02]テ",
    "BW_common.157.0072": "[BD02]ト",
    "BW_common.157.0073": "[BD02]ナ",
    "BW_common.157.0074": "[BD02]ニ",
    "BW_common.157.0075": "[BD02]ヌ",
    "BW_common.157.0076": "[BD02]ネ",
    "BW_common.157.0077": "[BD02]ノ",
    "BW_common.157.0078": "[BD02]ハ",
    "BW_common.157.0079": "[BD02]ヒ",
    "BW_common.157.0080": "[BD02]フ",
    "BW_common.157.0081": "[BD02]へ",
    "BW_common.157.0082": "[BD02]ホ",
    "BW_common.157.0083": "[BD02]マ",
    "BW_common.157.0084": "[BD02]ミ",
    "BW_common.157.0085": "[BD02]ム",
    "BW_common.157.0086": "[BD02]メ",
    "BW_common.157.0087": "[BD02]モ",
    "BW_common.157.0088": "[BD02]ヤ",
    "BW_common.157.0089": "[BD02]ユ",
    "BW_common.157.0090": "[BD02]ヨ",
    "BW_common.157.0091": "[BD02]ラ",
    "BW_common.157.0092": "[BD02]リ",
    "BW_common.157.0093": "[BD02]ル",
    "BW_common.157.0094": "[BD02]レ",
    "BW_common.157.0095": "[BD02]ロ",
    "BW_common.157.0096": "[BD02]ワ",
    "BW_common.157.0097": "交換は\nキャンセル　されました",
    "BW_common.157.0098": "そのポケモンを　交換すると\n冒険できなく　なっちゃうよ！",
    "BW_common.157.0099": "相手が　交換できない\nポケモンを　だしています",
    "BW_common.157.0100": "自分が　交換できない\nポケモンを　だしています",
    "BW_common.157.0101": "大切な技を　おぼえているので\n手持ち　から　はずせません",
    "BW_common.157.0102": "相手は　ポケモン交換を\nしたいようです",
    "BW_common.157.0103": "交換を　やめますか？",
    "BW_common.157.0104": "相手の　終了を　待っています……",
    "BW_common.157.0105": "タマゴ",
    "BW_common.157.0106": "ポケモンが　持っていた　メールを\nパソコンに　転送しました！",
    "BW_common.157.0107": "メールを　捨てますが\nよろしいですか？",
    "BW_common.157.0108": "メールボックスが　一杯です\n整理しますか？",
    "BW_common.157.0109": "メールを　捨てました",
    "BW_common.157.0110": "取った　メールを\nパソコンに　転送しました",
    "BW_common.157.0111": "相手は　メールを　受け取れません\n交換を　キャンセル　します",
    "BW_common.157.0112": "[0101,0000]",
    "BW_common.157.0113": "差し出すポケモンを　選んでください\nポケモンは　３匹まで選べます",
    "BW_common.157.0114": "[BD03,0000]選択中",
    "BW_common.157.0115": "[BD03,0000]決定済み",
    "BW_common.157.0116": "[BD03,0000]終了待ち",
    "BW_common.157.0117": "[0100,0000]の\nほしいポケモン",
    "BW_common.157.0118": "すべてのポケモン",
    "BW_common.157.0119": "かっこいいポケモン",
    "BW_common.157.0120": "かわいいポケモン",
    "BW_common.157.0121": "こわいポケモン",
    "BW_common.157.0122": "へんなポケモン",
    "BW_common.157.0123": "なんでも",
    "BW_common.157.0124": "Ｌｖ．１からＬｖ．４９",
    "BW_common.157.0125": "Ｌｖ．５０",
    "BW_common.157.0126": "Ｌｖ．５１から１００",
    "BW_common.157.0127": "決定",
    "BW_common.157.0128": "[0100,0000]",
    "BW_common.157.0129": "[0102,0000]を　[0100,0001]へ　送ります！！\nバイバイ　[0102,0000]！",
    "BW_common.157.0130": "[0102,0000]を　[0100,0001]に　返します！\nありがとう　[0102,0000]！",
    "BW_common.157.0131": "[0100,0000]の　ところから\n[0102,0001]が　戻ってきた！",
    "BW_common.157.0132": "おかえり　[0102,0001]！",
    "BW_common.157.0133": "交換希望",
    "BW_common.157.0134": "差し出す　ポケモンを　選んでください\nポケモンは　３匹まで選べます",
    "BW_common.157.0135": "相手に　差し出す　ポケモンは\nこれで　いいですか？",
    "BW_common.157.0136": "相手の　選択を　待っています\nしばらく　お待ちください……",
    "BW_common.157.0137": "お互い　差し出した　ポケモンから\n１匹　選びます　よろしいですか？",
    "BW_common.157.0138": "相手が　交換を\nキャンセルしました",
    "BW_common.157.0139": "相手は　交換したがっているようです",
    "BW_common.157.0140": "交換を終了しますか？",
    "BW_common.157.0141": "交換を終了しました",
    "BW_common.157.0142": "そのポケモンを　相手に\n差し出すことは　できません",
    "BW_common.157.0143": "自分に　交換できない　ポケモンがいます\nもう一度　選び直してください",
    "BW_common.157.0144": "相手に　交換できない　ポケモンがいます\nもう一度　選び直してください",
    "BW_common.157.0145": "欲しいポケモンを　相手の　差し出した\nポケモンから　１匹　選んでください",
    "BW_common.157.0146": "「[0102,0000]」と　自分の「[0102,0001]」を\n交換します　よろしいですか？",
    "BW_common.157.0147": "相手が　交換を　キャンセルしました\nもう一度　選び直してください",
    "BW_common.157.0148": "相手に　差し出した\nポケモンを　変更しますか？",
    "BW_common.157.0149": "交換を　キャンセルしました\nもう一度　選び直してください",
    "BW_common.157.0150": "交換を　キャンセルしました\nもう一度　１匹　選び直してください",
    "BW_common.157.0151": "相手が　交換を　キャンセルしました\nもう一度　１匹　選び直してください",
    "BW_common.157.0152": "[0102,0000]を　預けます",
    "BW_common.157.0153": "[0102,0001]を　引き取った",
    "BW_common.157.0154": "接続を　きる",
    "BW_common.157.0155": "[0102,0000]を　[0100,0001]へ\n送ります",
    "BW_common.157.0156": "[0100,0000]から　[0102,0001]が\n送られてきました",
    "BW_common.157.0157": "通信を　失敗しました",
    "BW_common.157.0158": "通信エラーが発生しました。\n（１３２８０）",
    "BW_common.157.0159": "通信エラーが発生しました。\n（１３２８１）",
    "BW_common.157.0160": "通信エラーが発生しました。\n（１３２８２）",
    "BW_common.157.0161": "通信エラーが発生しました。\n（１３２８３）",
    "BW_common.157.0162": "？？？"
}
