{
    "BW_common.161.0000": "野生の　ポケモンと　少し\n遭遇しやすく　なります\n効果は　３分　です",
    "BW_common.161.0001": "野生の　ポケモンと　とても\n遭遇しやすく　なります\n効果は　３分　です",
    "BW_common.161.0002": "野生の　ポケモンと　かなり\n遭遇しやすく　なります\n効果は　３分　です",
    "BW_common.161.0003": "野生の　ポケモンと　少し\n遭遇しづらく　なります\n効果は　３分　です",
    "BW_common.161.0004": "野生の　ポケモンと　とても\n遭遇しづらく　なります\n効果は　３分　です",
    "BW_common.161.0005": "野生の　ポケモンと　かなり\n遭遇しづらく　なります\n効果は　３分　です",
    "BW_common.161.0006": "歩いているときに　タマゴが\n少し　かえりやすく　なります\n効果は　３分　です",
    "BW_common.161.0007": "歩いているときに　タマゴが\nとても　かえりやすく　なります\n効果は　３分　です",
    "BW_common.161.0008": "歩いているときに　タマゴが\nかなり　かえりやすく　なります\n効果は　３分　です",
    "BW_common.161.0009": "ポケモンが　少し\nなつきやすく　なります\n効果は　３分　です",
    "BW_common.161.0010": "ポケモンが　とても\nなつきやすく　なります\n効果は　３分　です",
    "BW_common.161.0011": "ポケモンが　かなり\nなつきやすく　なります\n効果は　３分　です",
    "BW_common.161.0012": "フレンドリィショップで\n１０％オフの　安売りが　はじまります\n効果は　３分　です",
    "BW_common.161.0013": "フレンドリィショップで\n２５％オフの　安売りが　はじまります\n効果は　３分　です",
    "BW_common.161.0014": "フレンドリィショップで\n５０％オフの　安売りが　はじまります\n効果は　３分　です",
    "BW_common.161.0015": "このパワーを　使うと\nその場で　先頭にいる　ポケモンの\n体力が　少し　回復します",
    "BW_common.161.0016": "このパワーを　使うと\nその場で　先頭にいる　ポケモンの\n体力が　とても　回復します",
    "BW_common.161.0017": "このパワーを　使うと\nその場で　先頭にいる　ポケモンの\n体力が　かなり　回復します",
    "BW_common.161.0018": "このパワーを　使うと\nその場で　先頭にいる　ポケモンの\nＰＰが　少し　回復します",
    "BW_common.161.0019": "このパワーを　使うと\nその場で　先頭にいる　ポケモンの\nＰＰが　とても　回復します",
    "BW_common.161.0020": "このパワーを　使うと\nその場で　先頭にいる　ポケモンの\nＰＰが　かなり　回復します",
    "BW_common.161.0021": "戦ったあと　もらえる　経験値が\n少し　上がります\n効果は　３分　です",
    "BW_common.161.0022": "戦ったあと　もらえる　経験値が\nとても　上がります\n効果は　３分　です",
    "BW_common.161.0023": "戦ったあと　もらえる　経験値が\nかなり　上がります\n効果は　３分　です",
    "BW_common.161.0024": "戦ったあと　もらえる　経験値が\n少し　減ります\n効果は　３分　です",
    "BW_common.161.0025": "戦ったあと　もらえる　経験値が\nとても　減ります\n効果は　３分　です",
    "BW_common.161.0026": "戦ったあと　もらえる　経験値が\nかなり　減ります\n効果は　３分　です",
    "BW_common.161.0027": "戦ったあと　もらえる　おこづかいが\n少し　上がります\n効果は　３分　です",
    "BW_common.161.0028": "戦ったあと　もらえる　おこづかいが\nとても　上がります\n効果は　３分　です",
    "BW_common.161.0029": "戦ったあと　もらえる　おこづかいが\nかなり　上がります\n効果は　３分　です",
    "BW_common.161.0030": "ポケモンを　捕獲する　確率が\n少し　上がります\n効果は　３分　です",
    "BW_common.161.0031": "ポケモンを　捕獲する　確率が\nとても　上がります\n効果は　３分　です",
    "BW_common.161.0032": "ポケモンを　捕獲する　確率が\nかなり　上がります\n効果は　３分　です",
    "BW_common.161.0033": "歩いているときに　タマゴが\nかなり　かえりやすく　なります\n効果は　３０分　です",
    "BW_common.161.0034": "フレンドリィショップで\n５０％オフの　安売りが　はじまります\n効果は　３０分　です",
    "BW_common.161.0035": "ポケモンが　かなり\nなつきやすく　なります\n効果は　３０分　です",
    "BW_common.161.0036": "戦ったあと　もらえる　経験値が\nかなり　上がります\n効果は　３０分　です",
    "BW_common.161.0037": "戦ったあと　もらえる　おこづかいが\nかなり　上がります\n効果は　３０分　です",
    "BW_common.161.0038": "ポケモンを　捕獲する　確率が\nかなり　上がります\n効果は　３０分　です",
    "BW_common.161.0039": "このパワーを　受け取ると\n手持ちにいる　全ての　ポケモンが\n全快します",
    "BW_common.161.0040": "歩いているときに　タマゴが\nかなり　かえりやすく　なります\n効果は　６０分　です",
    "BW_common.161.0041": "フレンドリィショップで\n５０％オフの　安売りが　はじまります\n効果は　６０分　です",
    "BW_common.161.0042": "ポケモンが　かなり\nなつきやすく　なります\n効果は　６０分　です",
    "BW_common.161.0043": "戦ったあと　もらえる　経験値が\nかなり　上がります\n効果は　６０分　です",
    "BW_common.161.0044": "戦ったあと　もらえる　おこづかいが\nかなり　上がります\n効果は　６０分　です",
    "BW_common.161.0045": "ポケモンを　捕獲する　確率が\nかなり　上がります\n効果は　６０分　です",
    "BW_common.161.0046": "ダミー",
    "BW_common.161.0047": "ダミー"
}
