{
    "B2W2_common.397.0000": "一般屬性……\\f\n只有格鬥屬性的攻擊\n效果拔群。\\f",
    "B2W2_common.397.0001": "一般和格鬥屬性……\\f\n格鬥、飛行和超能力屬性的攻擊\n效果拔群。\\f",
    "B2W2_common.397.0002": "一般和飛行屬性……\\f\n岩石、電和冰屬性的攻擊\n效果拔群。\\f",
    "B2W2_common.397.0003": "一般和毒屬性……\\f\n地上和超能力屬性的攻擊\n效果拔群。\\f",
    "B2W2_common.397.0004": "一般和地上屬性……\\f\n格鬥、水、草和\n冰屬性的攻擊\\r\n效果拔群。\\f",
    "B2W2_common.397.0005": "一般和岩石屬性……\\f\n地上、鋼和水\n草、格鬥屬性的攻擊\\r\n效果拔群。\\f\n由於被較多屬性剋制，\n就需要由訓練師來彌補了。\\f",
    "B2W2_common.397.0006": "一般和蟲屬性……\\f\n飛行、岩石和炎屬性的攻擊\n效果拔群。\\f",
    "B2W2_common.397.0007": "一般和幽靈屬性……\\f\n只有惡屬性的攻擊\n效果拔群。\\f",
    "B2W2_common.397.0008": "一般和鋼屬性……\\f\n地上、炎和格鬥屬性的攻擊\n效果拔群。\\f",
    "B2W2_common.397.0009": "一般和炎屬性……\\f\n格鬥、地上、岩石和\n水屬性的攻擊\\r\n效果拔群。\\f",
    "B2W2_common.397.0010": "一般和水屬性……\\f\n格鬥、草和電屬性的攻擊\n效果拔群。\\f",
    "B2W2_common.397.0011": "一般和草屬性……\\f\n格鬥、飛行、毒、\n蟲、炎和冰屬性的攻擊\\r\n效果拔群。\\f\n由於被較多屬性剋制，\n就需要由訓練師來彌補了。\\f",
    "B2W2_common.397.0012": "一般和電屬性……\\f\n格鬥和地上屬性的攻擊\n效果拔群。\\f",
    "B2W2_common.397.0013": "一般和超能力屬性……\\f\n蟲和惡屬性的攻擊\n效果拔群。\\f",
    "B2W2_common.397.0014": "一般和冰屬性……\\f\n岩石、鋼、炎和\n格鬥屬性的攻擊\\r\n效果拔群。\\f",
    "B2W2_common.397.0015": "一般和龍屬性……\\f\n格鬥、冰和龍屬性的攻擊\n效果拔群。\\f",
    "B2W2_common.397.0016": "一般和惡屬性……\\f\n蟲和格鬥屬性的攻擊\n效果拔群。\\f",
    "B2W2_common.397.0017": "格鬥屬性……\\f\n飛行和超能力屬性的攻擊\n效果拔群。\\f",
    "B2W2_common.397.0018": "格鬥和飛行屬性……\\f\n飛行、電、超能力和\n冰屬性的攻擊\\r\n效果拔群。\\f",
    "B2W2_common.397.0019": "格鬥和毒屬性……\\f\n飛行、地上和超能力屬性的攻擊\n效果拔群。\\f",
    "B2W2_common.397.0020": "格鬥和地上屬性……\\f\n飛行、水、草、\n超能力和冰屬性的攻擊\\r\n效果拔群。\\f\n由於被較多屬性剋制，\n就需要由訓練師來彌補了。\\f",
    "B2W2_common.397.0021": "格鬥和岩石屬性……\\f\n格鬥、地上、鋼、\n水、草和超能力屬性的攻擊\\r\n效果拔群。\\f\n由於被較多屬性剋制，\n就需要由訓練師來彌補了。\\f",
    "B2W2_common.397.0022": "格鬥和蟲屬性……\\f\n炎、超能力和飛行屬性的攻擊\n效果拔群。\\f",
    "B2W2_common.397.0023": "格鬥和幽靈屬性……\\f\n飛行、幽靈和超能力屬性的攻擊\n效果拔群。\\f",
    "B2W2_common.397.0024": "格鬥和鋼屬性……\\f\n格鬥、地上和炎屬性的攻擊\n效果拔群。\\f",
    "B2W2_common.397.0025": "格鬥和炎屬性……\\f\n飛行、地上、水和\n超能力屬性的攻擊\\r\n效果拔群。\\f",
    "B2W2_common.397.0026": "格鬥和水屬性……\\f\n飛行、草、電和\n超能力屬性的攻擊\\r\n效果拔群。\\f",
    "B2W2_common.397.0027": "格鬥和草屬性……\\f\n毒、炎、超能力、\n冰和飛行屬性的攻擊\\r\n效果拔群。\\f\n由於被較多屬性剋制，\n就需要由訓練師來彌補了。\\f",
    "B2W2_common.397.0028": "格鬥和電屬性……\\f\n地上和超能力屬性的攻擊\n效果拔群。\\f",
    "B2W2_common.397.0029": "格鬥和超能力屬性……\\f\n飛行和幽靈屬性的攻擊\n效果拔群。\\f",
    "B2W2_common.397.0030": "格鬥和冰屬性……\\f\n格鬥、飛行、鋼、\n炎和超能力屬性的攻擊\\r\n效果拔群。\\f\n由於被較多屬性剋制，\n就需要由訓練師來彌補了。\\f",
    "B2W2_common.397.0031": "格鬥和龍屬性……\\f\n飛行、超能力、冰和\n龍屬性的攻擊\\r\n效果拔群。\\f",
    "B2W2_common.397.0032": "格鬥和惡屬性……\\f\n格鬥和飛行屬性的攻擊\n效果拔群。\\f",
    "B2W2_common.397.0033": "飛行屬性……\\f\n岩石、電和冰屬性的攻擊\n效果拔群。\\f",
    "B2W2_common.397.0034": "飛行和毒屬性……\\f\n岩石、電、超能力和\n冰屬性的攻擊\\r\n效果拔群。\\f",
    "B2W2_common.397.0035": "飛行和地上屬性……\\f\n水和冰屬性的攻擊\n效果拔群。\\f",
    "B2W2_common.397.0036": "飛行和岩石屬性……\\f\n岩石、鋼、水、\n電和冰屬性的攻擊\\r\n效果拔群。\\f\n由於被較多屬性剋制，\n就需要由訓練師來彌補了。\\f",
    "B2W2_common.397.0037": "飛行和蟲屬性……\\f\n飛行、炎、電、\n冰和岩石屬性的攻擊\\r\n效果拔群。\\f\n由於被較多屬性剋制，\n就需要由訓練師來彌補了。\\f",
    "B2W2_common.397.0038": "飛行和幽靈屬性……\\f\n岩石、幽靈、電、\n冰和惡屬性的攻擊\\r\n效果拔群。\\f\n由於被較多屬性剋制，\n就需要由訓練師來彌補了。\\f",
    "B2W2_common.397.0039": "飛行和鋼屬性……\\f\n炎和電屬性的攻擊\n效果拔群。\\f",
    "B2W2_common.397.0040": "飛行和炎屬性……\\f\n水、電和岩石屬性的攻擊\n效果拔群。\\f",
    "B2W2_common.397.0041": "飛行和水屬性……\\f\n岩石和電屬性的攻擊\n效果拔群。\\f",
    "B2W2_common.397.0042": "飛行和草屬性……\\f\n飛行、毒、岩石、\n炎和冰屬性的攻擊\\r\n效果拔群。\\f\n由於被較多屬性剋制，\n就需要由訓練師來彌補了。\\f",
    "B2W2_common.397.0043": "飛行和電屬性……\\f\n岩石和冰屬性的攻擊\n效果拔群。\\f",
    "B2W2_common.397.0044": "飛行和超能力屬性……\\f\n岩石、幽靈、電、\n冰和惡屬性的攻擊\\r\n效果拔群。\\f\n由於被較多屬性剋制，\n就需要由訓練師來彌補了。\\f",
    "B2W2_common.397.0045": "飛行和冰屬性……\\f\n鋼、炎、電和\n岩石屬性的攻擊\\r\n效果拔群。\\f",
    "B2W2_common.397.0046": "飛行和龍屬性……\\f\n岩石　龍和冰屬性的攻擊\n效果拔群。\\f",
    "B2W2_common.397.0047": "飛行和惡屬性……\\f\n岩石、電和冰屬性的攻擊\n效果拔群。\\f",
    "B2W2_common.397.0048": "毒屬性……\\f\n地上和超能力屬性的攻擊\n效果拔群。\\f",
    "B2W2_common.397.0049": "毒和地上屬性……\\f\n地上、水、超能力和\n冰屬性的攻擊\\r\n效果拔群。\\f",
    "B2W2_common.397.0050": "毒和岩石屬性……\\f\n鋼、水、超能力和\n地上屬性的攻擊\\r\n效果拔群。\\f",
    "B2W2_common.397.0051": "毒和蟲屬性……\\f\n飛行、岩石、炎和\n超能力屬性的攻擊\\r\n效果拔群。\\f",
    "B2W2_common.397.0052": "毒和幽靈屬性……\\f\n地上、幽靈、超能力和\n惡屬性的攻擊\\r\n效果拔群。\\f",
    "B2W2_common.397.0053": "毒和鋼屬性……\\f\n炎和地上屬性的攻擊\n效果拔群。\\f",
    "B2W2_common.397.0054": "毒和炎屬性……\\f\n岩石、水、超能力和\n地上屬性的攻擊\\r\n效果拔群。\\f",
    "B2W2_common.397.0055": "毒和水屬性……\\f\n地上、電和超能力屬性的攻擊\n效果拔群。\\f",
    "B2W2_common.397.0056": "毒和草屬性……\\f\n飛行、炎、超能力和\n冰屬性的攻擊\\r\n效果拔群。\\f",
    "B2W2_common.397.0057": "毒和電屬性……\\f\n超能力和地上屬性的攻擊\n效果拔群。\\f",
    "B2W2_common.397.0058": "毒和超能力屬性……\\f\n地上、幽靈和惡屬性的攻擊\n效果拔群。\\f",
    "B2W2_common.397.0059": "毒和冰屬性……\\f\n地上、岩石、鋼、\n炎和超能力屬性的攻擊\\r\n效果拔群。\\f\n由於被較多屬性剋制，\n就需要由訓練師來彌補了。\\f",
    "B2W2_common.397.0060": "毒和龍屬性……\\f\n地上、超能力、冰和\n龍屬性的攻擊\\r\n效果拔群。\\f",
    "B2W2_common.397.0061": "毒和惡屬性……\\f\n只有地上屬性的攻擊\n效果拔群。\\f",
    "B2W2_common.397.0062": "地上屬性……\\f\n水、草和冰屬性的攻擊\n效果拔群。\\f",
    "B2W2_common.397.0063": "地上和岩石屬性……\\f\n格鬥、地上、鋼、\n冰、水和草屬性的攻擊\\r\n效果拔群。\\f\n由於被較多屬性剋制，\n就需要由訓練師來彌補了。\\f",
    "B2W2_common.397.0064": "地上和蟲屬性……\\f\n飛行、水、炎和\n冰屬性的攻擊\\r\n效果拔群。\\f",
    "B2W2_common.397.0065": "地上和幽靈屬性……\\f\n幽靈、水、草、\n冰和惡屬性的攻擊\\r\n效果拔群。\\f\n由於被較多屬性剋制，\n就需要由訓練師來彌補了。\\f",
    "B2W2_common.397.0066": "地上和鋼屬性……\\f\n格鬥、地上、水和\n炎屬性的攻擊\\r\n效果拔群。\\f",
    "B2W2_common.397.0067": "地上和炎屬性……\\f\n地上和水屬性的攻擊\n效果拔群。\\f",
    "B2W2_common.397.0068": "地上和水屬性……\\f\n只有草屬性的攻擊\n效果拔群。\\f",
    "B2W2_common.397.0069": "地上和草屬性……\\f\n飛行、蟲、炎和\n冰屬性的攻擊\\r\n效果拔群。\\f",
    "B2W2_common.397.0070": "地上和電屬性……\\f\n地上、水、草和\n冰屬性的攻擊\\r\n效果拔群。\\f",
    "B2W2_common.397.0071": "地上和超能力屬性……\\f\n蟲、幽靈、水、\n草、冰和惡屬性的攻擊\\r\n效果拔群。\\f\n由於被較多屬性剋制，\n就需要由訓練師來彌補了。\\f",
    "B2W2_common.397.0072": "地上和冰屬性……\\f\n格鬥、鋼、水、\n炎和草屬性的攻擊\\r\n效果拔群。\\f\n由於被較多屬性剋制，\n就需要由訓練師來彌補了。\\f",
    "B2W2_common.397.0073": "地上和龍屬性……\\f\n龍和冰屬性的攻擊\n效果拔群。\\f",
    "B2W2_common.397.0074": "地上和惡屬性……\\f\n格鬥、蟲、水、\n草和冰屬性的攻擊\\r\n效果拔群。\\f\n由於被較多屬性剋制，\n就需要由訓練師來彌補了。\\f",
    "B2W2_common.397.0075": "岩石屬性……\\f\n格鬥、地上、鋼、\n水和草屬性的攻擊\\r\n效果拔群。\\f\n由於被較多屬性剋制，\n就需要由訓練師來彌補了。\\f",
    "B2W2_common.397.0076": "岩石和蟲屬性……\\f\n岩石、鋼和水屬性的攻擊\n效果拔群。\\f",
    "B2W2_common.397.0077": "岩石和幽靈屬性……\\f\n地上、幽靈、鋼、\n水、草和惡屬性的攻擊\\r\n效果拔群。\\f",
    "B2W2_common.397.0078": "岩石和鋼屬性……\\f\n水、格鬥和地上屬性的攻擊\n效果拔群。\\f",
    "B2W2_common.397.0079": "岩石和炎屬性……\\f\n格鬥、岩石、地上和\n水屬性的攻擊\\r\n效果拔群。\\f",
    "B2W2_common.397.0080": "岩石和水屬性……\\f\n格鬥、地上、電和\n草屬性的攻擊\\r\n效果拔群。\\f",
    "B2W2_common.397.0081": "岩石和草屬性……\\f\n格鬥　蟲　鋼和\n冰屬性的攻擊\\r\n效果拔群。\\f",
    "B2W2_common.397.0082": "岩石和電屬性……\\f\n格鬥、水、草和\n地上屬性的攻擊\\r\n效果拔群。\\f",
    "B2W2_common.397.0083": "岩石和超能力屬性……\\f\n地上、蟲、幽靈、\n鋼、水、草和惡屬性的攻擊\\r\n效果拔群。\\f\n由於被較多屬性剋制，\n就需要由訓練師來彌補了。\\f",
    "B2W2_common.397.0084": "岩石和冰屬性……\\f\n地上、岩石、水、\n草、格鬥和鋼屬性的攻擊\\r\n效果拔群。\\f\n由於被較多屬性剋制，\n就需要由訓練師來彌補了。\\f",
    "B2W2_common.397.0085": "岩石和龍屬性……\\f\n格鬥、地上、鋼、\n冰和龍屬性的攻擊\\r\n效果拔群。\\f\n由於被較多屬性剋制，\n就需要由訓練師來彌補了。\\f",
    "B2W2_common.397.0086": "岩石和惡屬性……\\f\n地上、蟲、鋼、\n水、草和格鬥屬性的攻擊\\r\n效果拔群。\\f\n由於被較多屬性剋制，\n就需要由訓練師來彌補了。\\f",
    "B2W2_common.397.0087": "蟲屬性……\\f\n飛行、岩石和炎屬性的攻擊\n效果拔群。\\f",
    "B2W2_common.397.0088": "蟲和幽靈屬性……\\f\n飛行、岩石、幽靈、\n炎和惡屬性的攻擊\\r\n效果拔群。\\f\n由於被較多屬性剋制，\n就需要由訓練師來彌補了。\\f",
    "B2W2_common.397.0089": "蟲和鋼屬性……\\f\n只有炎屬性的攻擊\n效果拔群。\\f",
    "B2W2_common.397.0090": "蟲和炎屬性……\\f\n飛行、水和岩石屬性的攻擊\n效果拔群。\\f",
    "B2W2_common.397.0091": "蟲和水屬性……\\f\n飛行、岩石和電屬性的攻擊\n效果拔群。\\f",
    "B2W2_common.397.0092": "蟲和草屬性……\\f\n毒、岩石、蟲、\n冰、飛行和炎屬性的攻擊\\r\n效果拔群。\\f\n由於被較多屬性剋制，\n就需要由訓練師來彌補了。\\f",
    "B2W2_common.397.0093": "蟲和電屬性……\\f\n岩石和炎屬性的攻擊\n效果拔群。\\f",
    "B2W2_common.397.0094": "蟲和超能力屬性……\\f\n飛行、岩石、蟲、\n幽靈、炎和惡屬性的攻擊\\r\n效果拔群。\\f\n由於被較多屬性剋制，\n就需要由訓練師來彌補了。\\f",
    "B2W2_common.397.0095": "蟲和冰屬性……\\f\n飛行、鋼、岩石和\n炎屬性的攻擊\\r\n效果拔群。\\f",
    "B2W2_common.397.0096": "蟲和龍屬性……\\f\n飛行、岩石、冰和\n龍屬性的攻擊\\r\n效果拔群。\\f",
    "B2W2_common.397.0097": "蟲和惡屬性……\\f\n飛行、岩石、蟲和\n炎屬性的攻擊\\r\n效果拔群。\\f",
    "B2W2_common.397.0098": "幽靈屬性……\\f\n幽靈和惡屬性的攻擊\n效果拔群。\\f",
    "B2W2_common.397.0099": "幽靈和鋼屬性……\\f\n地上和炎屬性的攻擊\n效果拔群。\\f",
    "B2W2_common.397.0100": "幽靈和炎屬性……\\f\n地上、岩石、幽靈、\n水和惡屬性的攻擊\\r\n效果拔群。\\f\n由於被較多屬性剋制，\n就需要由訓練師來彌補了。\\f",
    "B2W2_common.397.0101": "幽靈和水屬性……\\f\n幽靈、草、電和\n惡屬性的攻擊\\r\n效果拔群。\\f",
    "B2W2_common.397.0102": "幽靈和草屬性……\\f\n飛行、幽靈、炎、\n冰和惡屬性的攻擊\\r\n效果拔群。\\f\n由於被較多屬性剋制，\n就需要由訓練師來彌補了。\\f",
    "B2W2_common.397.0103": "幽靈和電屬性……\\f\n地上　幽靈和惡屬性的攻擊\n效果拔群。\\f",
    "B2W2_common.397.0104": "幽靈和超能力屬性……\\f\n幽靈和惡屬性的攻擊\n效果拔群。\\f",
    "B2W2_common.397.0105": "幽靈和冰屬性……\\f\n岩石、幽靈、鋼、\n炎和惡屬性的攻擊\\r\n效果拔群。\\f\n由於被較多屬性剋制，\n就需要由訓練師來彌補了。\\f",
    "B2W2_common.397.0106": "幽靈和龍屬性……\\f\n幽靈、冰、龍和\n惡屬性的攻擊\\r\n效果拔群。\\f",
    "B2W2_common.397.0107": "幽靈和惡屬性……\\f\n沒有弱點的屬性，\n真是少見啊。\\f",
    "B2W2_common.397.0108": "鋼屬性……\\f\n格鬥、地上和炎屬性的攻擊\n效果拔群。\\f",
    "B2W2_common.397.0109": "鋼和炎屬性……\\f\n格鬥、水和地上屬性的攻擊\n效果拔群。\\f",
    "B2W2_common.397.0110": "鋼和水屬性……\\f\n格鬥、地上和電屬性的攻擊\n效果拔群。\\f",
    "B2W2_common.397.0111": "鋼和草屬性……\\f\n格鬥和炎屬性的攻擊\n效果拔群。\\f",
    "B2W2_common.397.0112": "鋼和電屬性……\\f\n格鬥、炎和地上屬性的攻擊\n效果拔群。\\f",
    "B2W2_common.397.0113": "鋼和超能力屬性……\\f\n地上和炎屬性的攻擊\n效果拔群。\\f",
    "B2W2_common.397.0114": "鋼和冰屬性……\\f\n地上、格鬥和炎屬性的攻擊\n效果拔群。\\f",
    "B2W2_common.397.0115": "鋼和龍屬性……\\f\n格鬥和地上屬性的攻擊\n效果拔群。\\f",
    "B2W2_common.397.0116": "鋼和惡屬性……\\f\n地上、炎和格鬥屬性的攻擊\n效果拔群。\\f",
    "B2W2_common.397.0117": "炎屬性……\\f\n地上、岩石和水屬性的攻擊\n效果拔群。\\f",
    "B2W2_common.397.0118": "炎和水屬性……\\f\n地上、岩石和電屬性的攻擊\n效果拔群。\\f",
    "B2W2_common.397.0119": "炎和草屬性……\\f\n飛行、毒和岩石屬性的攻擊\n效果拔群。\\f",
    "B2W2_common.397.0120": "炎和電屬性……\\f\n岩石、水和地上屬性的攻擊\n效果拔群。\\f",
    "B2W2_common.397.0121": "炎和超能力屬性……\\f\n地上、岩石、幽靈、\n水和惡屬性的攻擊\\r\n效果拔群。\\f\n由於被較多屬性剋制，\n就需要由訓練師來彌補了。\\f",
    "B2W2_common.397.0122": "炎和冰屬性……\\f\n格鬥、地上、水和\n岩石屬性的攻擊\\r\n效果拔群。\\f",
    "B2W2_common.397.0123": "炎和龍屬性……\\f\n地上、岩石和龍屬性的攻擊\n效果拔群。\\f",
    "B2W2_common.397.0124": "炎和惡屬性……\\f\n格鬥、地上、岩石和　\n水屬性的攻擊\\r\n效果拔群。\\f",
    "B2W2_common.397.0125": "水屬性……\\f\n草和電屬性的攻擊\n效果拔群。\\f",
    "B2W2_common.397.0126": "水和草屬性……\\f\n飛行、毒和蟲屬性的攻擊\n效果拔群。\\f",
    "B2W2_common.397.0127": "水和電屬性……\\f\n地上和草屬性的攻擊\n效果拔群。\\f",
    "B2W2_common.397.0128": "水和超能力屬性……\\f\n蟲、幽靈、草、\n電和惡屬性的攻擊\\r\n效果拔群。\\f\n由於被較多屬性剋制，\n就需要由訓練師來彌補了。\\f",
    "B2W2_common.397.0129": "水和冰屬性……\\f\n格鬥、岩石、草和\n電屬性的攻擊\\r\n效果拔群。\\f",
    "B2W2_common.397.0130": "水和龍屬性……\\f\n只有龍屬性的攻擊\n效果拔群。\\f",
    "B2W2_common.397.0131": "水和惡屬性……\\f\n格鬥、蟲、草和\n電屬性的攻擊\\r\n效果拔群。\\f",
    "B2W2_common.397.0132": "草屬性……\\f\n飛行、毒、蟲、\n炎和冰屬性的攻擊\\r\n效果拔群。\\f\n由於被較多屬性剋制，\n就需要由訓練師來彌補了。\\f",
    "B2W2_common.397.0133": "草和電屬性……\\f\n毒、蟲、炎和\n冰屬性的攻擊\\r\n效果拔群。\\f",
    "B2W2_common.397.0134": "草和超能力屬性……\\f\n飛行、毒、幽靈、\n炎、冰、惡和蟲屬性的攻擊\\r\n效果拔群。\\f\n由於被較多屬性剋制，\n就需要由訓練師來彌補了。\\f",
    "B2W2_common.397.0135": "草和冰屬性……\\f\n格鬥、飛行、毒、\n岩石、蟲、鋼和炎屬性的攻擊\\r\n效果拔群。\\f\n由於被較多屬性剋制，\n就需要由訓練師來彌補了。\\f",
    "B2W2_common.397.0136": "草和龍屬性……\\f\n飛行、毒、蟲、\n龍和冰屬性的攻擊\\r\n效果拔群。\\f\n由於被較多屬性剋制，\n就需要由訓練師來彌補了。\\f",
    "B2W2_common.397.0137": "草和惡屬性……\\f\n格鬥、飛行、毒、\n炎、冰和蟲屬性的攻擊\\r\n效果拔群。\\f\n由於被較多屬性剋制，\n就需要由訓練師來彌補了。\\f",
    "B2W2_common.397.0138": "電屬性……\\f\n只有地上屬性的攻擊\n效果拔群。\\f",
    "B2W2_common.397.0139": "電和超能力屬性……\\f\n地上、蟲、幽靈和\n惡屬性的攻擊\\r\n效果拔群。\\f",
    "B2W2_common.397.0140": "電和冰屬性……\\f\n格鬥、地上、岩石和\n炎屬性的攻擊\\r\n效果拔群。\\f",
    "B2W2_common.397.0141": "電和龍屬性……\\f\n地上、冰和龍屬性的攻擊\n效果拔群。\\f",
    "B2W2_common.397.0142": "電和惡屬性……\\f\n格鬥、地上和蟲屬性的攻擊\n效果拔群。\\f",
    "B2W2_common.397.0143": "超能力屬性……\\f\n蟲、幽靈和惡屬性的攻擊\n效果拔群。\\f",
    "B2W2_common.397.0144": "超能力和冰屬性……\\f\n岩石、蟲、幽靈、\n鋼、炎和惡屬性的攻擊\\r\n效果拔群。\\f\n由於被較多屬性剋制，\n就需要由訓練師來彌補了。\\f",
    "B2W2_common.397.0145": "超能力和龍屬性……\\f\n蟲、幽靈、冰、\n龍和惡屬性的攻擊\\r\n效果拔群。\\f\n由於被較多屬性剋制，\n就需要由訓練師來彌補了。\\f",
    "B2W2_common.397.0146": "超能力和惡屬性……\\f\n只有蟲屬性的攻擊\n效果拔群。\\f",
    "B2W2_common.397.0147": "冰屬性……\\f\n格鬥、岩石、鋼和\n炎屬性的攻擊\\r\n效果拔群。\\f",
    "B2W2_common.397.0148": "冰和龍屬性……\\f\n格鬥、岩石、鋼和\n龍屬性的攻擊\\r\n效果拔群。\\f",
    "B2W2_common.397.0149": "冰和惡屬性……\\f\n岩石、蟲、鋼、\n炎和格鬥屬性的攻擊\\r\n效果拔群。\\f\n由於被較多屬性剋制，\n就需要由訓練師來彌補了。\\f",
    "B2W2_common.397.0150": "龍屬性……\\f\n冰和龍屬性的攻擊\n效果拔群。\\f",
    "B2W2_common.397.0151": "龍和惡屬性……\\f\n格鬥、蟲、冰和\n龍屬性的攻擊\\r\n效果拔群。\\f",
    "B2W2_common.397.0152": "惡屬性……\\f\n格鬥和蟲屬性的攻擊\n效果拔群。\\f"
}
