{
  "Pt.029.0000": "装扮一下你的宝可梦吧！\\f\n去２楼的话，可以用试衣间\n让宝可梦戴上饰品，\\r\n帮它们打扮！",
  "Pt.029.0001": "这里是宝可梦抽签专柜！\n接待员就是我淑姿。\\f\n只要签上的号码\n和客人您的宝可梦的ＩＤ一致，\\r\n就能获得豪华奖品！\\f\n要试试宝可梦抽签吗？",
  "Pt.029.0002": "今天的抽签已经结束，\n请您明天再来！",
  "Pt.029.0003": "好的。\n期待您的下次光临。",
  "Pt.029.0004": "那就确认一下今天宝可梦抽签\n有没有中奖吧！\\f\n………………\n………………\\f\n",
  "Pt.029.0005": "中奖号码是：\n[0136,0000]！\\f\n来看看您的宝可梦的ＩＤ\n是否与号码一致吧！\\f\n",
  "Pt.029.0006": "恭喜恭喜！\\f\n您带着的\n[0101,0000]的ＩＤ\\r\n与号码有一致的数字！\\f\n",
  "Pt.029.0007": "恭喜恭喜！\\f\n您寄放在电脑里的\n[0101,0000]的ＩＤ\\r\n与号码有一致的数字！\\f\n",
  "Pt.029.0008": "非常遗憾，\n您没有任何ＩＤ与号码一致……",
  "Pt.029.0009": "最后１位数字一致，\n请收下４等奖的奖品！\\f\n",
  "Pt.029.0010": "在试衣间\n能够使用的背景增加了。",
  "Pt.029.0011": "最后２位数字一致，\n请收下３等奖的奖品！\\f\n",
  "Pt.029.0012": "最后３位数字一致，\n请收下２等奖的奖品！\\f\n",
  "Pt.029.0013": "最后４位数字一致，\n请收下１等奖的奖品！\\f\n",
  "Pt.029.0014": "居然最后５位数字全都一致！\n特等奖！您获得了特等奖！\\f\n……啊，我兴奋得都\n忘了给您拿奖品了。\\r\n请您收下奖品！\\f\n",
  "Pt.029.0015": "……咦？\n看来您的道具已经放满了。\\f\n请整理道具后再来。",
  "Pt.029.0016": "[0103,0000]您来了啊，\n我一直在等着您呢！\\f\n这是为您留的奖品，\n请收下！",
  "Pt.029.0017": "期待您的下次光临！\n您的淑姿在这里等着哦！",
  "Pt.029.0018": "这里是宝可梦抽签专柜。\\f\n想要再抽一次吗？",
  "Pt.029.0019": "你的努力都有留下记录哦，\n比如连胜的纪录，\\r\n捉到了多少只宝可梦等等。\\f\n只要去３楼就可以\n查看大家的记录。",
  "Pt.029.0020": "我还是投放个广告吧！\\f\n这样会有更多顾客\n来光顾百货店吧！",
  "Pt.029.0021": "电视上在采访形形色色的训练家。\\f\n大家都想听\n强大训练家们的经验之谈。\\f\n个人希望能采访一下道馆馆主或\n宝可梦联盟中强大的\\r\n四天王！"
}